pydop/__init__.py
pydop/fm_configuration.py
pydop/fm_constraint.py
pydop/fm_diagram.py
pydop/fm_result.py
pydop/mpl.py
pydop/spl.py
pydop/utils.py
pydop/operations/modules.py
pydop-1.0.dist-info/LICENSE
pydop-1.0.dist-info/METADATA
pydop-1.0.dist-info/WHEEL
pydop-1.0.dist-info/entry_points.txt
pydop-1.0.dist-info/top_level.txt
pydop-1.0.dist-info/RECORD
