Metadata-Version: 2.1
Name: pydop
Version: 1.0
Summary: Python package for the creation of delta-oriented Software Product Lines.
Author-email: Michael Lienhardt <michael.lienhardt@onera.fr>
Project-URL: Homepage, https://github.com/onera/pydop
Project-URL: Bug Tracker, https://github.com/onera/pydop/issues
Project-URL: Documentation, https://github.com/onera/pydop
Project-URL: Source Code, https://github.com/onera/pydop
Keywords: Software Product Lines,Multi-Software Product Lines,Delta-Oriented Programming,Variability,Software Engineering
Platform: Linux
Platform: Mac OSX
Platform: Windows
Platform: Unix
Classifier: Development Status :: 4 - Beta
Classifier: Intended Audience :: Developers
Classifier: Intended Audience :: Science/Research
Classifier: License :: OSI Approved :: GNU Lesser General Public License v3 (LGPLv3)
Classifier: Operating System :: OS Independent
Classifier: Programming Language :: Python :: 3
Classifier: Programming Language :: Python :: 3.8
Classifier: Programming Language :: Python :: 3.9
Classifier: Programming Language :: Python :: 3.10
Classifier: Programming Language :: Python :: 3.11
Classifier: Programming Language :: Python :: 3 :: Only
Classifier: Topic :: Software Development :: Libraries :: Python Modules
Classifier: Topic :: Software Development :: Code Generators
Requires-Python: >=3.8
License-File: LICENSE
Requires-Dist: networkx >=3.0
